scream/__init__.py
scream/detect_changed_packages.py
scream/monorepo.py
scream/package.py
scream/utils.py
scream/cli/__init__.py
scream/cli/main.py
scream/commands/__init__.py
scream/commands/deploy.py
scream/commands/init.py
scream/commands/install.py
scream/commands/new_package.py
scream/commands/test.py
scream/files/__init__.py
scream/files/deploy.py
scream/files/docs.py
scream/files/git.py
scream/files/module.py
scream/files/readme.py
scream/files/scream.py
scream/files/setup.py
scream/files/tox.py
scream/files/util.py
scream-0.0.34.data/scripts/detect_parent_branch.sh
scream-0.0.34.dist-info/LICENSE
scream-0.0.34.dist-info/METADATA
scream-0.0.34.dist-info/WHEEL
scream-0.0.34.dist-info/entry_points.txt
scream-0.0.34.dist-info/top_level.txt
scream-0.0.34.dist-info/RECORD
