Metadata-Version: 2.1
Name: scream
Version: 0.0.34
Summary: An opinionated CLI tool for Python monorepo MGMT.
Home-page: https://github.com/r-kells/scream
Author: Ryan Kelly
Author-email: ryan.kelly.md@gmail.com
License: UNKNOWN
Platform: UNKNOWN
Classifier: Programming Language :: Python :: 2
Classifier: Programming Language :: Python :: 3
Classifier: License :: OSI Approved :: MIT License
Classifier: Operating System :: OS Independent
Requires-Dist: flake8 (==3.6.0)
Requires-Dist: pep8-naming (==0.7.0)
Requires-Dist: coverage
Requires-Dist: tox (==3.13.2)
Requires-Dist: wheel
